rest_collection/__init__.py
rest_collection/api/__init__.py
rest_collection/api/abc/__init__.py
rest_collection/api/abc/filter.py
rest_collection/api/abc/filter_operator/__init__.py
rest_collection/api/abc/filter_operator/abc.py
rest_collection/api/abc/filter_operator/deserializer.py
rest_collection/api/abc/limit.py
rest_collection/api/abc/order_by.py
rest_collection/api/abc/relation.py
rest_collection/api/abc/request.py
rest_collection/api/alias/__init__.py
rest_collection/api/alias/alias.py
rest_collection/api/alias/aliased.py
rest_collection/api/exc.py
rest_collection/api/filter/__init__.py
rest_collection/api/filter/expression.py
rest_collection/api/filter/parser.py
rest_collection/api/filter_operator/__init__.py
rest_collection/api/filter_operator/operator/__init__.py
rest_collection/api/filter_operator/operator/comparison.py
rest_collection/api/filter_operator/operator/content.py
rest_collection/api/filter_operator/operator/other.py
rest_collection/api/filter_operator/registry/__init__.py
rest_collection/api/filter_operator/registry/container.py
rest_collection/api/filter_operator/registry/default.py
rest_collection/api/order_by.py
rest_collection/api/param/__init__.py
rest_collection/api/param/container.py
rest_collection/api/param/context.py
rest_collection/api/param/schema.py
rest_collection/api/pointer/__init__.py
rest_collection/api/pointer/container.py
rest_collection/api/pointer/factory.py
rest_collection/api/pointer/identity.py
rest_collection/api/pointer/registry.py
rest_collection/api/pointer/sa_mapper.py
rest_collection/api/request/__init__.py
rest_collection/api/request/filter.py
rest_collection/api/request/limit.py
rest_collection/api/request/main.py
rest_collection/api/request/order_by.py
rest_collection/api/request/relation.py
rest_collection/api/utils.py
rest_collection/container/__init__.py
rest_collection/container/alias.py
rest_collection/container/chunk.py
rest_collection/container/weakref.py
rest_collection/exc.py
rest_collection/py.typed
rest_collection-0.9.0.dist-info/LICENSE.txt
rest_collection-0.9.0.dist-info/WHEEL
rest_collection-0.9.0.dist-info/METADATA
rest_collection-0.9.0.dist-info/RECORD
